m2_rec2taps-0.9-py3.7-nspkg.pth
m2/rec2taps/__init__.py
m2/rec2taps/cli.py
m2/rec2taps/defaults.py
m2/rec2taps/errors.py
m2_rec2taps-0.9.dist-info/LICENSE
m2_rec2taps-0.9.dist-info/METADATA
m2_rec2taps-0.9.dist-info/WHEEL
m2_rec2taps-0.9.dist-info/entry_points.txt
m2_rec2taps-0.9.dist-info/namespace_packages.txt
m2_rec2taps-0.9.dist-info/top_level.txt
m2_rec2taps-0.9.dist-info/RECORD
