Metadata-Version: 2.1
Name: m2-rec2taps
Version: 0.9
Summary: Utility to obtain tap times from a tapping recording
Home-page: https://github.com/m2march/rec2taps
Author: Martin "March" Miguel
Author-email: m2.march@gmail.com
License: UNKNOWN
Platform: UNKNOWN
Requires-Dist: numpy
Requires-Dist: scipy
